{"public_key": {"type": "RSA", "value": "-----BEGIN PUBLIC KEY-----\nMIIBIjANBgkqhkiG9w0BAQEFAAOCAQ8AMIIBCgKCAQEA2waMSsWSVVgDaA797e2h\n245wZmU411a7MCmdIcR3aHQd4phVOm2uiCl/0wkLLpHygoTdmDmJ5DssQdBIHNJ5\nsNjPhtYu8Le+zYTlvFFmoa00wPRzYWoS3TpmHKTlVKM5Sgo6PtKqZEJgURUWqsLB\nSytXN75/sDSEfC9AEoRZLEE+RM2tVd3k0vgilhagqVz2WzDljEUq/C6pCFLKWHOg\nNGbouXw/p4nC1Oc7JDdUsAJPPrA8b+dJ6hlmp5FLleJnA2bYLtszt8OaB5DoqSHQ\nZVV9WxLawCvVNU6reiXrYkh9J28OCmeYunkNWqUSdNXCPxSyWCErd/C71d2XAj3k\nmwIDAQAB\n-----END PUBLIC KEY-----"}, "web_color_scheme": {"foreground": "#ffffff", "primary": "#000000", "background": "#000000", "secondary": "#ffffff"}, "focus_area": {"CA": [], "US": []}, "links": [{"href": "http://www.librarysimplified.org/iclicenses.html", "type": "text/html", "rel": "license"}, {"href": "https://circulation.librarysimplified.org/CLASSICS/loans/", "type": "application/atom+xml;profile=opds-catalog;kind=acquisition", "rel": "http://opds-spec.org/shelf"}, {"href": "https://circulation.librarysimplified.org/CLASSICS/patrons/me/", "type": "vnd.librarysimplified/user-profile+json", "rel": "http://librarysimplified.org/terms/rel/user-profile"}, {"href": "mailto:gethelp+simplye-collection@nypl.org", "rel": "http://librarysimplified.org/rel/designated-agent/copyright"}, {"href": "mailto:gethelp+simplye-collection@nypl.org", "type": null, "rel": "help"}, {"href": "http://librarysimplified.org/", "type": "text/html", "rel": "alternate"}, {"href": "https://circulation.librarysimplified.org/CLASSICS/groups/1832", "type": "application/atom+xml;profile=opds-catalog;kind=acquisition", "rel": "start"}], "title": "The SimplyE Collection", "service_area": {"CA": [], "US": []}, "announcements": [], "authentication": [{"type": "http://librarysimplified.org/terms/authentication/gate/coppa", "links": [{"href": "https://circulation.librarysimplified.org/CLASSICS/groups/1831", "type": "application/atom+xml;profile=opds-catalog;kind=acquisition", "rel": "http://librarysimplified.org/terms/rel/authentication/restriction-met"}, {"href": "https://circulation.librarysimplified.org/CLASSICS/groups/1832", "type": "application/atom+xml;profile=opds-catalog;kind=acquisition", "rel": "http://librarysimplified.org/terms/rel/authentication/restriction-not-met"}]}], "service_description": "A selection of classics and modern material available to anyone, with no library card necessary.", "color_scheme": "teal", "id": "https://circulation.librarysimplified.org/CLASSICS/authentication_document", "features": {"disabled": ["https://librarysimplified.org/rel/policy/reservations"], "enabled": []}}
